flexneuart/__init__.py
flexneuart/config.py
flexneuart/eval.py
flexneuart/utils.py
flexneuart/version.py
flexneuart/check_utils/__init__.py
flexneuart/check_utils/utils.py
flexneuart/data_convert/__init__.py
flexneuart/data_convert/utils.py
flexneuart/data_convert/biencoder/__init__.py
flexneuart/data_convert/biencoder/ance/__init__.py
flexneuart/data_convert/biencoder/ance/data.py
flexneuart/data_convert/biencoder/ance/models.py
flexneuart/data_convert/biencoder/tct_colbert_pass_v1/__init__.py
flexneuart/data_convert/biencoder/tct_colbert_pass_v1/models.py
flexneuart/data_convert/cranfield/__init__.py
flexneuart/data_convert/cranfield/utils.py
flexneuart/data_convert/msmarco/__init__.py
flexneuart/data_convert/msmarco/utils.py
flexneuart/data_convert/wikipedia_dpr/__init__.py
flexneuart/data_convert/wikipedia_dpr/utils.py
flexneuart/featextr_server/__init__.py
flexneuart/featextr_server/base.py
flexneuart/featextr_server/utils.py
flexneuart/featextr_server/python_generated/__init__.py
flexneuart/featextr_server/python_generated/protocol/ExternalScorer.py
flexneuart/featextr_server/python_generated/protocol/__init__.py
flexneuart/featextr_server/python_generated/protocol/constants.py
flexneuart/featextr_server/python_generated/protocol/ttypes.py
flexneuart/gen_exper_desc/__init__.py
flexneuart/gen_exper_desc/utils.py
flexneuart/indexing/__init__.py
flexneuart/indexing/utils.py
flexneuart/io/__init__.py
flexneuart/io/json.py
flexneuart/io/pack.py
flexneuart/io/qrels.py
flexneuart/io/queries.py
flexneuart/io/runs.py
flexneuart/io/stopwords.py
flexneuart/io/train_data.py
flexneuart/io/utils.py
flexneuart/io/vocab.py
flexneuart/ir_datasets/__init__.py
flexneuart/ir_datasets/base.py
flexneuart/ir_datasets/bert_tokenizer.py
flexneuart/ir_datasets/concat.py
flexneuart/ir_datasets/copy.py
flexneuart/ir_datasets/html_parser.py
flexneuart/ir_datasets/krovetz_stem_parser.py
flexneuart/ir_datasets/pipeline.py
flexneuart/ir_datasets/rename.py
flexneuart/ir_datasets/spacy.py
flexneuart-1.2.6.dist-info/LICENSE
flexneuart-1.2.6.dist-info/LICENSE.RankLib
flexneuart-1.2.6.dist-info/METADATA
flexneuart-1.2.6.dist-info/WHEEL
flexneuart-1.2.6.dist-info/top_level.txt
flexneuart-1.2.6.dist-info/RECORD
