Metadata-Version: 2.1
Name: flexneuart
Version: 1.2.6
Summary: FlexNeuART (flex-noo-art) is a Flexible classic and NeurAl Retrieval Toolkit
Author: Leonid Boytsov
Author-email: leo@boytsov.info
Requires-Python: >=3.6
License-File: LICENSE
License-File: LICENSE.RankLib
Requires-Dist: jupyter
Requires-Dist: pandas
Requires-Dist: einops
Requires-Dist: lxml
Requires-Dist: bson
Requires-Dist: tqdm
Requires-Dist: urllib3
Requires-Dist: pytools
Requires-Dist: beautifulsoup4
Requires-Dist: ir_datasets
Requires-Dist: pyjnius
Requires-Dist: torch
Requires-Dist: torchtext
Requires-Dist: transformers
Requires-Dist: spacy
Requires-Dist: sentence-transformers
Requires-Dist: sentencepiece
Requires-Dist: krovetzstemmer
Requires-Dist: numpy
Requires-Dist: thrift==0.13.0
Requires-Dist: typing-extensions
Requires-Dist: ujson
Requires-Dist: wandb
Requires-Dist: mtasklite
